tm_devices/__init__.py
tm_devices/commands/__init__.py
tm_devices/commands/afg3k_commands.py
tm_devices/commands/afg3kb_commands.py
tm_devices/commands/afg3kc_commands.py
tm_devices/commands/awg5200_commands.py
tm_devices/commands/awg5k_commands.py
tm_devices/commands/awg5kc_commands.py
tm_devices/commands/awg70ka_commands.py
tm_devices/commands/awg70kb_commands.py
tm_devices/commands/awg7k_commands.py
tm_devices/commands/awg7kc_commands.py
tm_devices/commands/daq6510_commands.py
tm_devices/commands/dmm6500_commands.py
tm_devices/commands/dmm7510_commands.py
tm_devices/commands/dpo2k_commands.py
tm_devices/commands/dpo2kb_commands.py
tm_devices/commands/dpo4k_commands.py
tm_devices/commands/dpo4kb_commands.py
tm_devices/commands/dpo5k_commands.py
tm_devices/commands/dpo5kb_commands.py
tm_devices/commands/dpo70kc_commands.py
tm_devices/commands/dpo70kd_commands.py
tm_devices/commands/dpo70kdx_commands.py
tm_devices/commands/dpo70ksx_commands.py
tm_devices/commands/dpo7ax_commands.py
tm_devices/commands/dpo7k_commands.py
tm_devices/commands/dpo7kc_commands.py
tm_devices/commands/dsa70kc_commands.py
tm_devices/commands/dsa70kd_commands.py
tm_devices/commands/gen_16x4xq_dpo/__init__.py
tm_devices/commands/gen_16x4xq_dpo/trigger.py
tm_devices/commands/gen_1nfb7e_dpo/__init__.py
tm_devices/commands/gen_1nfb7e_dpo/channelmapping.py
tm_devices/commands/gen_1nfb7e_dpo/counter.py
tm_devices/commands/gen_1nfb7e_dpo/errordetector.py
tm_devices/commands/gen_1nfb7e_dpo/idnmultiscope.py
tm_devices/commands/gen_1nfb7e_dpo/linktraining.py
tm_devices/commands/gen_1nfb7e_dpo/rosc.py
tm_devices/commands/gen_1nfb7e_dpo/trigger.py
tm_devices/commands/gen_22bw6e_dpo/__init__.py
tm_devices/commands/gen_22bw6e_dpo/acquire.py
tm_devices/commands/gen_22bw6e_dpo/auxin.py
tm_devices/commands/gen_22bw6e_dpo/auxout.py
tm_devices/commands/gen_22bw6e_dpo/bus.py
tm_devices/commands/gen_22bw6e_dpo/ch.py
tm_devices/commands/gen_22bw6e_dpo/data.py
tm_devices/commands/gen_22bw6e_dpo/diag.py
tm_devices-3.5.0.dist-info/LICENSE.md
tm_devices-3.5.0.dist-info/METADATA
tm_devices-3.5.0.dist-info/WHEEL
tm_devices-3.5.0.dist-info/entry_points.txt
tm_devices-3.5.0.dist-info/RECORD
