Metadata-Version: 2.1
Name: tm_devices
Version: 3.5.0
Summary: Manage connections and interactions with Test & Measurement devices.
Home-page: https://pypi.org/project/tm_devices/
License: Apache-2.0
Keywords: REST API,SCPI,TSP,Tektronix,Test & Measurement,VISA
Author: Tektronix
Author-email: opensource@tektronix.com
Maintainer: Tektronix
Maintainer-email: opensource@tektronix.com
Requires-Python: >=3.9.2,<3.14
Classifier: Development Status :: 5 - Production/Stable
Classifier: Intended Audience :: Developers
Classifier: Intended Audience :: Science/Research
Classifier: License :: OSI Approved :: Apache Software License
Classifier: Operating System :: OS Independent
Classifier: Programming Language :: Python :: 3
Classifier: Programming Language :: Python :: 3.10
Classifier: Programming Language :: Python :: 3.11
Classifier: Programming Language :: Python :: 3.12
Classifier: Programming Language :: Python :: 3.13
Classifier: Programming Language :: Python :: 3.9
Classifier: Topic :: Scientific/Engineering
Classifier: Topic :: Scientific/Engineering :: Interface Engine/Protocol Translator
Classifier: Topic :: System :: Hardware :: Hardware Drivers
Requires-Dist: colorlog (>=6.9.0,<7.0.0)
Requires-Dist: dc-schema (>=0.0.8,<0.0.9)
Requires-Dist: gpib-ctypes (>=0.3.0,<0.4.0)
Requires-Dist: jsonschema[format-nongpl] (>=4.23.0,<5.0.0)
Requires-Dist: libusb-package (>=1.0.26.0,<2.0.0.0,!=1.0.26.2)
Requires-Dist: packaging (>=24.0)
Requires-Dist: psutil (>=6.0.0)
Requires-Dist: pyserial (>=3.5,<4.0)
Requires-Dist: python-dateutil (>=2.8.2,<3.0.0)
Requires-Dist: pyusb (>=1.2.1,<2.0.0)
Requires-Dist: pyvicp (>=1.1.0,<2.0.0)
Requires-Dist: pyvisa (>=1.12.0,<2.0.0)
Requires-Dist: pyvisa-py (>=0.7.2,<0.8.0)
Requires-Dist: pyvisa-sim (>=0.6.0,<0.7.0)
Requires-Dist: pyyaml (>=6.0,<7.0)
Requires-Dist: requests (>=2.31.0,<3.0.0)
Requires-Dist: tomli (>=2.0.1,<3.0.0)
Requires-Dist: tomli-w (>=1.0.0,<2.0.0)
Requires-Dist: typing-extensions (>=4.10.0,<5.0.0)
Requires-Dist: tzlocal (>=5.2,<6.0)
Requires-Dist: urllib3 (>=2.0,<3.0)
Requires-Dist: zeroconf (>=0.148.0,<0.149.0)
Project-URL: Bug Tracker, https://github.com/tektronix/tm_devices/issues
Project-URL: Changelog, https://github.com/tektronix/tm_devices/blob/main/CHANGELOG.md
Project-URL: Documentation, https://tm-devices.readthedocs.io/stable/
Project-URL: Repository, https://github.com/tektronix/tm_devices
